mudderpy-0.1.5.dist-info/METADATA
mudderpy-0.1.5.dist-info/WHEEL
mudderpy/__init__.py
mudderpy/__init__.pyi
mudderpy/py.typed
mudderpy/mudderpy.pypy39-pp73-x86-linux-gnu.so
mudderpy-0.1.5.dist-info/RECORD
