Metadata-Version: 2.1
Name: mudderpy
Version: 0.1.5
Classifier: Programming Language :: Rust
Classifier: Programming Language :: Python :: Implementation :: CPython
Classifier: Programming Language :: Python :: Implementation :: PyPy
Summary: Generate lexicographically-spaced strings between two strings from pre-defined alphabets.
License: MIT
Requires-Python: >=3.7
Project-URL: Source Code, https://github.com/kevinhu/mudder
